{
  "id": "compliance-data-inventory-maintained",
  "name": "Data Inventory Maintained",
  "description": "The organization should maintain an inventory of personal data processing activities as required by privacy regulations",
  "effect": "forbid",
  "resource": "compliance_documents",
  "conditions": [
    "document_type == DATA_INVENTORY",
    "last_updated_days > 365"
  ],
  "severity": "medium",
  "remediation": "Create and maintain a data inventory/records of processing activities (ROPA) documenting all personal data processed",
  "remediation_steps": [
    "Identify all systems that process personal data",
    "Document data categories, purposes, and legal basis",
    "Identify data recipients and transfers",
    "Document retention periods",
    "Identify technical and organizational security measures",
    "Review and update at least annually"
  ],
  "tags": [
    "compliance",
    "privacy",
    "data-inventory",
    "gdpr",
    "ropa"
  ],
  "risk_categories": [
    "MISCONFIGURATION"
  ],
  "frameworks": [
    {
      "name": "GDPR",
      "controls": ["Article 30"]
    },
    {
      "name": "ISO 27701",
      "controls": ["7.2.8"]
    },
    {
      "name": "SOC 2",
      "controls": ["P1.1"]
    },
    {
      "name": "CCPA",
      "controls": ["1798.100"]
    }
  ]
}
