{
  "id": "identity-google-workspace-duplicate-membership-assignment",
  "name": "Google Workspace Duplicate Membership Assignments",
  "description": "Detects duplicate Google Workspace group membership rows for the same member and group.",
  "severity": "LOW",
  "category": "identity",
  "resource_type": "google_workspace_group_member",
  "frameworks": [
    {
      "name": "SOC 2",
      "controls": [
        "CC6.1"
      ]
    },
    {
      "name": "ISO 27001:2022",
      "controls": [
        "A.5.17"
      ]
    }
  ],
  "enabled": true,
  "query": "SELECT m.group_id, LOWER(TRIM(m.email)) AS member_key, COUNT(*) AS membership_count FROM google_workspace_group_members m WHERE m.group_id IS NOT NULL AND COALESCE(TRIM(m.email), '') != '' GROUP BY m.group_id, LOWER(TRIM(m.email)) HAVING COUNT(*) > 1",
  "remediation": "Deduplicate repeated membership rows and validate provisioning idempotency in sync pipelines.",
  "tags": [
    "google-workspace",
    "identity",
    "groups",
    "data-integrity"
  ]
}
